badgify/__init__.py
badgify/admin.py
badgify/commands.py
badgify/compat.py
badgify/exceptions.py
badgify/recipe.py
badgify/registry.py
badgify/settings.py
badgify/signals.py
badgify/urls.py
badgify/utils.py
badgify/views.py
badgify/management/__init__.py
badgify/management/commands/__init__.py
badgify/management/commands/badgify_reset.py
badgify/management/commands/badgify_stats.py
badgify/management/commands/badgify_sync.py
badgify/migrations/0001_initial.py
badgify/migrations/__init__.py
badgify/models/__init__.py
badgify/models/award.py
badgify/models/badge.py
badgify/models/base/__init__.py
badgify/models/base/award.py
badgify/models/base/badge.py
badgify/templatetags/__init__.py
badgify/templatetags/badgify_tags.py
badgify/tests/__init__.py
badgify/tests/badgify_recipes.py
badgify/tests/mixins.py
badgify/tests/models.py
badgify/tests/recipes.py
badgify/tests/settings.py
badgify/tests/test_commands.py
badgify/tests/test_models.py
badgify/tests/test_registry.py
badgify/tests/test_templatetags.py
badgify/tests/test_views.py
badgify/tests/migrations/0001_initial.py
badgify/tests/migrations/__init__.py
example/__init__.py
example/admin.py
example/badgify_recipes.py
example/models.py
example/settings.py
example/urls.py
example/wsgi.py
example/management/__init__.py
example/management/commands/__init__.py
example/management/commands/create_fixtures.py
example/migrations/0001_initial.py
example/migrations/__init__.py
django_badgify-0.5.0.dist-info/AUTHORS
django_badgify-0.5.0.dist-info/LICENSE
django_badgify-0.5.0.dist-info/METADATA
django_badgify-0.5.0.dist-info/WHEEL
django_badgify-0.5.0.dist-info/top_level.txt
django_badgify-0.5.0.dist-info/RECORD
