Metadata-Version: 2.1
Name: django-badgify
Version: 0.5.0
Summary: A reusable application to create your own badge engine using Django
Home-page: http://github.com/ulule/django-badgify
Author: Gilles Fabio
Author-email: gilles.fabio@gmail.com
License: UNKNOWN
Platform: UNKNOWN
Classifier: Environment :: Web Environment
Classifier: Framework :: Django
Classifier: Intended Audience :: Developers
Classifier: License :: OSI Approved :: MIT License
Classifier: Operating System :: OS Independent
Classifier: Programming Language :: Python
Classifier: Programming Language :: Python :: 3
Classifier: Programming Language :: Python :: 3.8
Classifier: Programming Language :: Python :: 3.9
Classifier: Topic :: Utilities
License-File: LICENSE
License-File: AUTHORS
Requires-Dist: Pillow
Requires-Dist: pytz
Requires-Dist: six
